Metadata-Version: 2.1
Name: tap-marketo
Version: 2.6.1
Summary: Singer.io tap for extracting data from the Marketo API
Home-page: http://singer.io
Author: Stitch
Classifier: Programming Language :: Python :: 3 :: Only
License-File: LICENSE
Requires-Dist: singer-python==6.0.0
Requires-Dist: requests==2.31.0
Requires-Dist: pendulum==1.2.0
Requires-Dist: freezegun>=0.3.9
Requires-Dist: requests_mock>=1.3.0
Requires-Dist: backoff==2.2.1
Provides-Extra: dev
Requires-Dist: ipdb==0.11; extra == "dev"
